{
	"$type": "System.Collections.Generic.Dictionary`2[[System.String, mscorlib],[AvatarPiece, Assembly-CSharp]], mscorlib",
	"Default" : {
		"$type": "AvatarPiece, Assembly-CSharp",
		"id": "Default",
		"path": "empty",
		"swatchType": "clothes",
		"weight": 1,
	},
	"Clothes 1" : {
		"$type": "AvatarPiece, Assembly-CSharp",
		"id": "Clothes 1",
		"path": "clothes1",
		"swatchType": "clothes",
		"weight": 1,
	},
	"Clothes 2" : {
		"$type": "AvatarPiece, Assembly-CSharp",
		"id": "Clothes 2",
		"path": "clothes2",
		"swatchType": "clothes",
		"weight": 1,
	},
	"Clothes 3" : {
		"$type": "AvatarPiece, Assembly-CSharp",
		"id": "Clothes 3",
		"path": "clothes3",
		"swatchType": "clothes",
		"weight": 1,
	},
	"Clothes 4" : {
		"$type": "AvatarPiece, Assembly-CSharp",
		"id": "Clothes 4",
		"path": "clothes4",
		"swatchType": "clothes",
		"weight": 1,
	},
	"Clothes 5" : {
		"$type": "AvatarPiece, Assembly-CSharp",
		"id": "Clothes 5",
		"path": "clothes5",
		"swatchType": "clothes",
		"weight": 1,
	},
	"Clothes 6" : {
		"$type": "AvatarPiece, Assembly-CSharp",
		"id": "Clothes 6",
		"path": "clothes6",
		"swatchType": "clothes",
		"weight": 1,
	},
	"Clothes 7" : {
		"$type": "AvatarPiece, Assembly-CSharp",
		"id": "Clothes 7",
		"path": "clothes7",
		"swatchType": "clothes",
		"weight": 1,
	},
	"Clothes 8" : {
		"$type": "AvatarPiece, Assembly-CSharp",
		"id": "Clothes 8",
		"path": "clothes8",
		"swatchType": "clothes",
		"weight": 1,
	},
	"Clothes 9" : {
		"$type": "AvatarPiece, Assembly-CSharp",
		"id": "Clothes 9",
		"path": "clothes9",
		"swatchType": "clothes",
		"weight": 1,
	},
}